{
  "description": "Mapping for bitfinex trade history file",
  "map": [
    {
      "id": "CDPVXFNLWJKY",
      "ns_id": "AGI"
    },
    {
      "id": "CFXPGNHTVZJW",
      "ns_id": "AID"
    },
    {
      "id": "CDLPFYJTZNXW",
      "ns_id": "ANS"
    },
    {
      "id": "CQTHFLYKGVPN",
      "ns_id": "ANT"
    },
    {
      "id": "CHFNLYGXWQKZ",
      "ns_id": "AVT"
    },
    {
      "id": "CHNWYVZTQFJX",
      "ns_id": "BAT"
    },
    {
      "id": "CWKHNDXQGFTP",
      "ns_id": "BCH"
    },
    {
      "id": "CQPGTDNYXKFV",
      "ns_id": "BCI"
    },
    {
      "id": "CPNZKQVLHTFW",
      "ns_id": "BT1"
    },
    {
      "id": "CJWKDFVXZYQH",
      "ns_id": "BT2"
    },
    {
      "id": "CJTFPXDVQHNG",
      "ns_id": "BTC"
    },
    {
      "id": "CFKZNTXJLVYW",
      "ns_id": "BTG"
    },
    {
      "id": "CVNPJZFLTKGQ",
      "ns_id": "BTU"
    },
    {
      "id": "CQLJDHKWNZXP",
      "ns_id": "DASH"
    },
    {
      "id": "CKNFLPZTJQGH",
      "ns_id": "DATA"
    },
    {
      "id": "CFNPJXGHKDYQ",
      "ns_id": "DTH"
    },
    {
      "id": "CQYXFLPJVHWG",
      "ns_id": "EDO"
    },
    {
      "id": "CHVGXYKFQJWL",
      "ns_id": "ELF"
    },
    {
      "from": "2018-06-02T22:00:00Z",
      "id": "CPXQGHKTDLYJ",
      "ns_id": "EOS"
    },
    {
      "id": "CTFLDWZYQKXG",
      "ns_id": "EOS",
      "to": "2018-06-02T22:00:00Z"
    },
    {
      "id": "CKPFHDWXZVGQ",
      "ns_id": "ETC"
    },
    {
      "id": "CPWTGZNVHKJF",
      "ns_id": "ETH"
    },
    {
      "id": "CXZVYWFTPQGJ",
      "ns_id": "ETP"
    },
    {
      "id": "CVKDPYQLNGJX",
      "ns_id": "FUN"
    },
    {
      "id": "CQNWYPFVZHGT",
      "ns_id": "GNT"
    },
    {
      "id": "CJPQKYNXZTGL",
      "ns_id": "IOT"
    },
    {
      "id": "CJNXVGZQLDFY",
      "ns_id": "LTC"
    },
    {
      "id": "CYLTXGQFHZWP",
      "ns_id": "MIT"
    },
    {
      "id": "CHTPLJNVGDWQ",
      "ns_id": "MNA"
    },
    {
      "id": "CDLPFYJTZNXW",
      "ns_id": "NEO"
    },
    {
      "id": "CWLNTJFYZQHX",
      "ns_id": "ODE"
    },
    {
      "id": "CNQYVDZWFPHJ",
      "ns_id": "OMG"
    },
    {
      "id": "CPKYVFQJNWZH",
      "ns_id": "PAI"
    },
    {
      "id": "CKPHZNTQWLYF",
      "ns_id": "QSH"
    },
    {
      "id": "CQFHKZYLGWNV",
      "ns_id": "QTUM"
    },
    {
      "id": "CJLDFWGKHNQX",
      "ns_id": "RCN"
    },
    {
      "id": "CFLYXPHZKTNV",
      "ns_id": "REP"
    },
    {
      "id": "CVKGNDZPQTFY",
      "ns_id": "RLC"
    },
    {
      "id": "CLWNDTJGVHQK",
      "ns_id": "SAN"
    },
    {
      "id": "CPNXFZKTLDWQ",
      "ns_id": "SNG"
    },
    {
      "id": "CGXWZQFVPKJH",
      "ns_id": "SNT"
    },
    {
      "id": "CPQNWKHZDVXT",
      "ns_id": "SPK"
    },
    {
      "id": "CLXHYGWNVPJZ",
      "ns_id": "STJ"
    },
    {
      "id": "CQPYKWLNHVFD",
      "ns_id": "TNB"
    },
    {
      "id": "CDVYLJGFXHZK",
      "ns_id": "TRX"
    },
    {
      "id": "CZYHDQPFNXWJ",
      "ns_id": "USD"
    },
    {
      "id": "CZYHDQPFNXWJ",
      "ns_id": "USDT"
    },
    {
      "id": "CYFXPHZJTKQN",
      "ns_id": "WAX"
    },
    {
      "id": "CDYZWFQLHTPX",
      "ns_id": "XLM"
    },
    {
      "id": "CLTJPFYZNVWG",
      "ns_id": "XMR"
    },
    {
      "id": "CDJXFTVWNLYH",
      "ns_id": "XRP"
    },
    {
      "id": "CKTHPFLVDYJG",
      "ns_id": "XVG"
    },
    {
      "id": "CDKVHXFLTGYQ",
      "ns_id": "YYW"
    },
    {
      "id": "CWKDPXJQHZGF",
      "ns_id": "ZEC"
    },
    {
      "id": "CGTNDFPLXYHZ",
      "ns_id": "ZRX"
    }
  ],
  "namespace": "bitfinex"
}
